{
  "id": "memento",
  "v": "v1",
  "ts": 1734636681824,
  "signature": "s4323.036041/4323.038594",
  "data": {
    "machineId": "c8ef2265f8676388228e7ac7ce8a2784b875527121944799733b3131c90a5142",
    "ts": 1734636681824,
    "log": [
      [
        1733636396965,
        0,
        "activate",
        1
      ],
      [
        1734555915495,
        0,
        "activate",
        1
      ],
      [
        1734556659817,
        0,
        "replace",
        1,
        "unneccessary",
        "unnecessary"
      ],
      [
        1734620978380,
        0,
        "activate",
        1
      ],
      [
        1734620990810,
        0,
        "activate",
        1
      ],
      [
        1734621088572,
        0,
        "activate",
        1
      ],
      [
        1734636681437,
        0,
        "activate",
        1
      ]
    ]
  }
}